MANIFEST.in
README.rst
README.txt
setup.cfg
setup.py
Products/__init__.py
Products.Quills.egg-info/PKG-INFO
Products.Quills.egg-info/SOURCES.txt
Products.Quills.egg-info/dependency_links.txt
Products.Quills.egg-info/entry_points.txt
Products.Quills.egg-info/namespace_packages.txt
Products.Quills.egg-info/not-zip-safe
Products.Quills.egg-info/requires.txt
Products.Quills.egg-info/top_level.txt
Products/Quills/IGNORE.txt
Products/Quills/LICENSE.txt
Products/Quills/README.txt
Products/Quills/TODO.txt
Products/Quills/Weblog.py
Products/Quills/WeblogEntry.py
Products/Quills/__init__.py
Products/Quills/config.py
Products/Quills/configure.zcml
Products/Quills/deprecationwarnings.zcml
Products/Quills/monkeypatches.py
Products/Quills/permissions.py
Products/Quills/rebuild_i18n.sh
Products/Quills/refresh.txt
Products/Quills/setuphandlers.py
Products/Quills/version.txt
Products/Quills/Extensions/Install.py
Products/Quills/browser/__init__.py
Products/Quills/browser/configure.zcml
Products/Quills/deprecated/MetaWeblogAPI.py
Products/Quills/deprecated/WeblogArchive.py
Products/Quills/deprecated/WeblogDrafts.py
Products/Quills/deprecated/WeblogTopic.py
Products/Quills/deprecated/__init__.py
Products/Quills/doc/UserGuide.txt
Products/Quills/locales/quills-manual.pot
Products/Quills/locales/quills.pot
Products/Quills/locales/cy/LC_MESSAGES/quills.po
Products/Quills/locales/da/LC_MESSAGES/quills.po
Products/Quills/locales/de/LC_MESSAGES/quills.po
Products/Quills/locales/en/LC_MESSAGES/quills.po
Products/Quills/locales/es/LC_MESSAGES/quills.po
Products/Quills/locales/eu/LC_MESSAGES/quills.po
Products/Quills/locales/fr/LC_MESSAGES/quills.po
Products/Quills/locales/it/LC_MESSAGES/quills.po
Products/Quills/locales/ja/LC_MESSAGES/quills.po
Products/Quills/locales/lt/LC_MESSAGES/quills.po
Products/Quills/locales/nl/LC_MESSAGES/quills.po
Products/Quills/locales/pt-br/LC_MESSAGES/quills.po
Products/Quills/locales/pt/LC_MESSAGES/quills.po
Products/Quills/locales/ru/LC_MESSAGES/quills.po
Products/Quills/locales/sr-Latn/LC_MESSAGES/quills.po
Products/Quills/locales/sr/LC_MESSAGES/quills.po
Products/Quills/migrations/__init__.py
Products/Quills/migrations/quills08to09.py
Products/Quills/migrations/quills09to15.py
Products/Quills/migrations/quills15to16.py
Products/Quills/migrations/quills16to17.py
