Metadata-Version: 1.1
Name: Products.Quills
Version: 1.8.1
Summary: A Blogging Suite for Plone.
Home-page: https://github.com/collective/Products.Quills
Author: Quills Team
Author-email: UNKNOWN
License: GPL
Download-URL: https://github.com/collective/Products.Quills
Keywords: plone blogging
Platform: UNKNOWN
Classifier: Development Status :: 5 - Production/Stable
Classifier: Framework :: Plone
Classifier: Framework :: Plone :: 3.2
Classifier: Framework :: Plone :: 3.3
Classifier: Framework :: Plone :: 4.0
Classifier: Framework :: Plone :: 4.1
Classifier: Framework :: Plone :: 4.2
Classifier: Framework :: Plone :: 4.3
Classifier: License :: OSI Approved :: GNU General Public License (GPL)
Classifier: Programming Language :: Python
Classifier: Topic :: Software Development :: Libraries :: Python Modules
